[
{"no":0,"poster":"p1.png","director":"롤랜드 에머리히","name":"인디펜던스 데이:리써전스","likes":106,"dislikes":12},
{"no":1,"poster":"p2.png","director":"이경미","name":"비밀은 없다","likes":106,"dislikes":12},
{"no":2,"poster":"p3.png","director":"존 파브로","name":"정글북","likes":106,"dislikes":12},
{"no":3,"poster":"p4.png","director":"박찬욱","name":"아가씨","likes":106,"dislikes":12},
{"no":4,"poster":"p5.png","director":"제임스 완","name":"컨저링2","likes":106,"dislikes":12},
{"no":5,"poster":"p6.png","director":"아리엘 브로멘","name":"크리미널","likes":106,"dislikes":12}
]